{
  "workflow": {
    "runNumber": 19,
    "repository": "tawanamohammadi/FilterMapIR",
    "commitSha": "fb165f12b73fcbddfda5e75ffb9fb2ccc299f025",
    "triggeredBy": "schedule",
    "actor": "tawanamohammadi",
    "runId": "20895272961",
    "branch": "main"
  },
  "timestamp": "2026-01-11T12:39:59Z",
  "runner": {
    "arch": "X64",
    "os": "Windows"
  },
  "scan": {
    "traceroute": false,
    "duration": "23.9291069",
    "date": "2026-01-11",
    "exitCode": "1",
    "deepScan": false
  }
}
